<?xml version="1.0" encoding="utf-8" ?><dwsync><file name="960_home_Image2.png" server="Macintosh HD/Applications/MAMP/htdocs/plife/" local="3443649660" remote="12033584252" /><file name="960_home_Image3.png" server="Macintosh HD/Applications/MAMP/htdocs/plife/" local="3443649660" remote="12033584252" /><file name="960_home_Image4.png" server="Macintosh HD/Applications/MAMP/htdocs/plife/" local="3443649660" remote="12033584252" /><file name="960_home_Image5.png" server="Macintosh HD/Applications/MAMP/htdocs/plife/" local="3443649660" remote="12033584252" /><file name="960_home_Image6.png" server="Macintosh HD/Applications/MAMP/htdocs/plife/" local="3443649660" remote="12033584252" /><file name="live-the-life.png" server="Macintosh HD/Applications/MAMP/htdocs/plife/" local="3444157980" remote="12034092572" /><file name="960_home_Subscribe.png" server="Macintosh HD/Applications/MAMP/htdocs/plife/" local="3444154020" remote="12034088612" /><file name="960_About.png" server="Macintosh HD/Applications/MAMP/htdocs/plife/" local="3443649660" remote="12033584252" /><file name="960_home_Blog.png" server="Macintosh HD/Applications/MAMP/htdocs/plife/" local="3443649660" remote="12033584252" /><file name="960_home_EmailAddress.png" server="Macintosh HD/Applications/MAMP/htdocs/plife/" local="3443649660" remote="12033584252" /><file name="960_home_FB.png" server="Macintosh HD/Applications/MAMP/htdocs/plife/" local="3443649660" remote="12033584252" /><file name="960_home_FBbig.png" server="Macintosh HD/Applications/MAMP/htdocs/plife/" local="3443649660" remote="12033584252" /><file name="960_home_Image1.png" server="Macintosh HD/Applications/MAMP/htdocs/plife/" local="3443649660" remote="12033584252" /><file name="960_home_Instagram.png" server="Macintosh HD/Applications/MAMP/htdocs/plife/" local="3443649660" remote="12033584252" /><file name="960_home_InstagramBig.png" server="Macintosh HD/Applications/MAMP/htdocs/plife/" local="3443649660" remote="12033584252" /><file name="960_home_LiftSlide.png" server="Macintosh HD/Applications/MAMP/htdocs/plife/" local="3443649660" remote="12033584252" /><file name="960_home_Logo.png" server="Macintosh HD/Applications/MAMP/htdocs/plife/" local="3443649660" remote="12033584252" /><file name="960_home_ReadMore.png" server="Macintosh HD/Applications/MAMP/htdocs/plife/" local="3443649660" remote="12033584252" /><file name="960_home_RightSlide.png" server="Macintosh HD/Applications/MAMP/htdocs/plife/" local="3443649660" remote="12033584252" /><file name="960_home_Twitter.png" server="Macintosh HD/Applications/MAMP/htdocs/plife/" local="3443649660" remote="12033584252" /><file name="960_home_TwitterBig.png" server="Macintosh HD/Applications/MAMP/htdocs/plife/" local="3443649660" remote="12033584252" /><file name="960_home_Video.png" server="Macintosh HD/Applications/MAMP/htdocs/plife/" local="3443649660" remote="12033584252" /><file name="960_home_Vimeo.png" server="Macintosh HD/Applications/MAMP/htdocs/plife/" local="3443649660" remote="12033584252" /><file name="960_home_VimeoBig.png" server="Macintosh HD/Applications/MAMP/htdocs/plife/" local="3443649660" remote="12033584252" /><file name="960_About.png" server="Untitled/Applications/MAMP/htdocs/p-life/" local="3443496387" remote="318763443836392899" /><file name="960_home_Blog.png" server="Untitled/Applications/MAMP/htdocs/p-life/" local="3442353938" remote="318763443835250450" /><file name="960_home_EmailAddress.png" server="Untitled/Applications/MAMP/htdocs/p-life/" local="3442354098" remote="318763443835250610" /><file name="960_home_FB.png" server="Untitled/Applications/MAMP/htdocs/p-life/" local="3442353518" remote="318763443835250030" /><file name="960_home_FBbig.png" server="Untitled/Applications/MAMP/htdocs/p-life/" local="3442354228" remote="318763443835250740" /><file name="960_home_Image1.png" server="Untitled/Applications/MAMP/htdocs/p-life/" local="3442353590" remote="318763443835250102" /><file name="960_home_Image2.png" server="Untitled/Applications/MAMP/htdocs/p-life/" local="3442353672" remote="318763443835250184" /><file name="960_home_Image3.png" server="Untitled/Applications/MAMP/htdocs/p-life/" local="3442353728" remote="318763443835250240" /><file name="960_home_Image4.png" server="Untitled/Applications/MAMP/htdocs/p-life/" local="3442353832" remote="318763443835250344" /><file name="960_home_Image5.png" server="Untitled/Applications/MAMP/htdocs/p-life/" local="3442353880" remote="318763443835250392" /><file name="960_home_Image6.png" server="Untitled/Applications/MAMP/htdocs/p-life/" local="3442354034" remote="318763443835250546" /><file name="960_home_Instagram.png" server="Untitled/Applications/MAMP/htdocs/p-life/" local="3442353256" remote="318763443835249768" /><file name="960_home_InstagramBig.png" server="Untitled/Applications/MAMP/htdocs/p-life/" local="3442354334" remote="318763443835250846" /><file name="960_home_LiftSlide.png" server="Untitled/Applications/MAMP/htdocs/p-life/" local="3442805026" remote="318763443835701538" /><file name="960_home_Logo.png" server="Untitled/Applications/MAMP/htdocs/p-life/" local="3442353208" remote="318763443835249720" /><file name="960_home_ReadMore.png" server="Untitled/Applications/MAMP/htdocs/p-life/" local="3442353984" remote="318763443835250496" /><file name="960_home_RightSlide.png" server="Untitled/Applications/MAMP/htdocs/p-life/" local="3442805076" remote="318763443835701588" /><file name="960_home_Subscribe.png" server="Untitled/Applications/MAMP/htdocs/p-life/" local="3444154020" remote="318763443837050532" /><file name="960_home_Twitter.png" server="Untitled/Applications/MAMP/htdocs/p-life/" local="3442353430" remote="318763443835249942" /><file name="960_home_TwitterBig.png" server="Untitled/Applications/MAMP/htdocs/p-life/" local="3442354262" remote="318763443835250774" /><file name="960_home_Video.png" server="Untitled/Applications/MAMP/htdocs/p-life/" local="3442353772" remote="318763443835250284" /><file name="960_home_Vimeo.png" server="Untitled/Applications/MAMP/htdocs/p-life/" local="3442353368" remote="318763443835249880" /><file name="960_home_VimeoBig.png" server="Untitled/Applications/MAMP/htdocs/p-life/" local="3442354296" remote="318763443835250808" /><file name="live-the-life.png" server="Untitled/Applications/MAMP/htdocs/p-life/" local="3444157980" remote="318763443837054492" /><file name="960_home_Subscribe.png" server="onearmbandit.in//privileged-life/" local="3444154020" remote="12034088612" /><file name="live-the-life.png" server="onearmbandit.in//privileged-life/" local="3444157980" remote="12034092572" /><file name="960_About.png" server="onearmbandit.in//privileged-life/" local="3443649660" remote="20623518844" /><file name="960_home_Blog.png" server="onearmbandit.in//privileged-life/" local="3443649660" remote="20623518844" /><file name="960_home_EmailAddress.png" server="onearmbandit.in//privileged-life/" local="3443649660" remote="20623518844" /><file name="960_home_FB.png" server="onearmbandit.in//privileged-life/" local="3443649660" remote="20623518844" /><file name="960_home_FBbig.png" server="onearmbandit.in//privileged-life/" local="3443649660" remote="20623518844" /><file name="960_home_Image1.png" server="onearmbandit.in//privileged-life/" local="3443649660" remote="20623518844" /><file name="960_home_Image2.png" server="onearmbandit.in//privileged-life/" local="3443649660" remote="20623518844" /><file name="960_home_Image3.png" server="onearmbandit.in//privileged-life/" local="3443649660" remote="20623518844" /><file name="960_home_Image4.png" server="onearmbandit.in//privileged-life/" local="3443649660" remote="20623518844" /><file name="960_home_Image5.png" server="onearmbandit.in//privileged-life/" local="3443649660" remote="20623518844" /><file name="960_home_Image6.png" server="onearmbandit.in//privileged-life/" local="3445199220" remote="16330101108" /><file name="960_home_Instagram.png" server="onearmbandit.in//privileged-life/" local="3443649660" remote="20623518844" /><file name="960_home_InstagramBig.png" server="onearmbandit.in//privileged-life/" local="3443649660" remote="20623518844" /><file name="960_home_LiftSlide.png" server="onearmbandit.in//privileged-life/" local="3443649660" remote="20623518844" /><file name="960_home_Logo.png" server="onearmbandit.in//privileged-life/" local="3443649660" remote="20623518844" /><file name="960_home_ReadMore.png" server="onearmbandit.in//privileged-life/" local="3443649660" remote="20623518844" /><file name="960_home_RightSlide.png" server="onearmbandit.in//privileged-life/" local="3443649660" remote="20623518844" /><file name="960_home_Twitter.png" server="onearmbandit.in//privileged-life/" local="3443649660" remote="20623518844" /><file name="960_home_TwitterBig.png" server="onearmbandit.in//privileged-life/" local="3443649660" remote="20623518844" /><file name="960_home_Video.png" server="onearmbandit.in//privileged-life/" local="3443649660" remote="20623518844" /><file name="960_home_Vimeo.png" server="onearmbandit.in//privileged-life/" local="3443649660" remote="20623518844" /><file name="960_home_VimeoBig.png" server="onearmbandit.in//privileged-life/" local="3443649660" remote="20623518844" /><file name=".DS_Store" server="Macintosh HD/Applications/MAMP/htdocs/plife/" local="3442858980" remote="12032793572" /><file name="lookbook_image.png" server="Macintosh HD/Applications/MAMP/htdocs/plife/" local="3446521087" remote="12036455679" /></dwsync>